simple_wkt/__init__.py
simple_wkt/geometries.py
simple_wkt/parsing.py
simple_wkt-1.2.1.dist-info/METADATA
simple_wkt-1.2.1.dist-info/WHEEL
simple_wkt-1.2.1.dist-info/top_level.txt
simple_wkt-1.2.1.dist-info/RECORD
